.gitignore
README.md
setup.cfg
setup.py
test.py
python_timeout.egg-info/PKG-INFO
python_timeout.egg-info/SOURCES.txt
python_timeout.egg-info/dependency_links.txt
python_timeout.egg-info/requires.txt
python_timeout.egg-info/top_level.txt
timeout/__init__.py
timeout/__pycache__/__init__.cpython-39.pyc