Metadata-Version: 2.1
Name: python-timeout
Version: 5.5
Summary: Random timeout between minimum and maximum values
Home-page: https://github.com/xjxckk/python-timeout/
